odoo10_addon_partner_bank_mail_thread-10.0.2.0.0-nspkg.pth
odoo/addons/partner_bank_mail_thread/README.rst
odoo/addons/partner_bank_mail_thread/__init__.py
odoo/addons/partner_bank_mail_thread/__manifest__.py
odoo/addons/partner_bank_mail_thread/i18n/partner_bank_mail_thread.pot
odoo/addons/partner_bank_mail_thread/models/__init__.py
odoo/addons/partner_bank_mail_thread/models/res_partner_bank.py
odoo/addons/partner_bank_mail_thread/readme/CONTRIBUTORS.rst
odoo/addons/partner_bank_mail_thread/readme/DESCRIPTION.rst
odoo/addons/partner_bank_mail_thread/readme/HISTORY.rst
odoo/addons/partner_bank_mail_thread/readme/INSTALL.rst
odoo/addons/partner_bank_mail_thread/readme/ROADMAP.rst
odoo/addons/partner_bank_mail_thread/readme/USAGE.rst
odoo/addons/partner_bank_mail_thread/static/description/icon.png
odoo/addons/partner_bank_mail_thread/static/description/index.html
odoo/addons/partner_bank_mail_thread/views/res_partner_bank.xml
odoo10_addon_partner_bank_mail_thread-10.0.2.0.0.dist-info/METADATA
odoo10_addon_partner_bank_mail_thread-10.0.2.0.0.dist-info/WHEEL
odoo10_addon_partner_bank_mail_thread-10.0.2.0.0.dist-info/namespace_packages.txt
odoo10_addon_partner_bank_mail_thread-10.0.2.0.0.dist-info/top_level.txt
odoo10_addon_partner_bank_mail_thread-10.0.2.0.0.dist-info/RECORD
