Metadata-Version: 2.1
Name: odoo10-addon-partner-bank-mail-thread
Version: 10.0.2.0.0
Summary: Enable a chatter on the partner bank accounts which will track updates done on a partner bank account
Home-page: https://github.com/OCA/partner-contact
Author: ACSONE SA/NV, Odoo Community Association (OCA)
Author-email: support@odoo-community.org
License: AGPL-3
Platform: UNKNOWN
Classifier: Programming Language :: Python
Classifier: Framework :: Odoo
Classifier: License :: OSI Approved :: GNU Affero General Public License v3
Requires-Python: ~=2.7
Requires-Dist: odoo (<10.1dev,>=10.0)
